reds/__init__.py
reds/reds.py
reds/task.py
reds/version.py
reds-0.1.9.dist-info/LICENSE
reds-0.1.9.dist-info/METADATA
reds-0.1.9.dist-info/WHEEL
reds-0.1.9.dist-info/top_level.txt
reds-0.1.9.dist-info/RECORD
